LICENCE
README.md
setup.py
MGE/Audio.py
MGE/Button.py
MGE/Camera.py
MGE/Global_Cache.py
MGE/Image.py
MGE/Internal_Window.py
MGE/Key_Maps.py
MGE/Keyboard.py
MGE/Line.py
MGE/MGE.py
MGE/Material.py
MGE/Mesh.py
MGE/Monitors.py
MGE/Mouse.py
MGE/Object2D.py
MGE/Object3D.py
MGE/Outside_Window.py
MGE/Platform.py
MGE/Sprite.py
MGE/Text.py
MGE/Texture.py
MGE/Vector.py
MGE/Version.py
MGE/Window.py
MGE/__init__.py
MGE.egg-info/PKG-INFO
MGE.egg-info/SOURCES.txt
MGE.egg-info/dependency_links.txt
MGE.egg-info/requires.txt
MGE.egg-info/top_level.txt