Metadata-Version: 2.1
Name: MGE
Version: 0.2.0
Summary: A library for creating games and interfaces graphics
Home-page: UNKNOWN
Author: Lucas Guimarães
Author-email: lucasguimaraes.commercial@gmail.com
License: MIT License
Keywords: MGE pygame
Platform: UNKNOWN
License-File: LICENCE
